uP.v
//CODIGO DEL BUS DRIVERS
module BD(input wire enable, input wire[3:0] A, output wire[3:0] data_bus);
  assign data_bus = enable ? A:4'bz; //CODIGO PARA QUE NO HAYA CONTENCION
endmodule

//CODIGO DEL ACCUMULATOR
module ACCU(input wire clk, reset, enable, input wire[3:0]A, output wire[3:0] accu);
//FLIPFLOP DE 4 BITS PARA EL ACCUMULATOR
  FFP4 F3(clk, reset, enable, A, accu);
endmodule

//CODIGO DE ALU
module ALU(input [3:0] A, B, input [2:0] R, output C, Ze, output [3:0] Y);
    reg [4:0] H;
    always @ (A, B, R)
    //SE AGREGAN LOS CALCULOS ARITMETICOS DE LA ALU
        case (R)
            3'b000: H = A;
            3'b001: H = A - B;
            3'b010: H = B;
            3'b011: H = A + B;
            3'b100: H = {1'b0, ~(A & B)};
            default: H = 5'b10101;
        endcase
//SE ASIGNAN VALORES
    assign Y = H[3:0];
    assign C = H[4];
    assign Ze = ~(H[3] | H[2] | H[1] | H[0]);
endmodule

//CODIGO DEL PC
module PC(input wire clk, reset, enable, loadbit, input wire[11:0] load ,output reg [11:0] PC);
//SE ASIGNA PARA QUE EL PC CUENTE Y SE PUEDA RESETEAR Y METER UN VALOR PREDETERMINADO
  always @ (posedge clk or posedge reset) begin
    if (reset)
      PC <= 12'b0;
    else if (loadbit)
      PC <= load;
    else if (enable)
      PC <= PC + 1;
  end
endmodule

//CODIGO DEL ROM
module ROM(input wire[11:0] A, output  wire[7:0] program_byte);
//EL CODIGO DE LA ROM PARA QUE LEA LA MEMORIA
  reg[7:0] Memoria[0:4096];
  initial
    $readmemh("memory.list", Memoria);
  assign program_byte = Memoria[A];
endmodule

//CODIGO DEL FETCH
module FETCH(input wire clk, reset, enable, input wire [7:0]A, output wire[3:0] instr, oprnd);
//2 FLIPFLOP PARA EL oprnd Y EL instr DE 4 BITS CADA UNO
 FFP4 F1(clk, reset, enable, A[7:4], instr);
 FFP4 F2(clk, reset, enable, A[3:0], oprnd);
endmodule

//CODIGO DEL FETCH
module DECODE(input [6:0] A, output [12:0] controls);

    reg [12:0] Y;
//SE ASIGNA LA NUBE COMBINACIONAL DEL DECODE
    always @ (A)
        casez(A)
            // any
            7'b????_??0: Y <= 13'b1000_000_001000;
            // JC
            7'b0000_1?1: Y <= 13'b0100_000_001000;
            7'b0000_0?1: Y <= 13'b1000_000_001000;
            // JNC
            7'b0001_1?1: Y <= 13'b1000_000_001000;
            7'b0001_0?1: Y <= 13'b0100_000_001000;
            // CMPI
            7'b0010_??1: Y <= 13'b0001_001_000010;
            // CMPM
            7'b0011_??1: Y <= 13'b1001_001_100000;
            // LIT
            7'b0100_??1: Y <= 13'b0011_010_000010;
            // IN
            7'b0101_??1: Y <= 13'b0011_010_000100;
            // LD
            7'b0110_??1: Y <= 13'b1011_010_100000;
            // ST
            7'b0111_??1: Y <= 13'b1000_000_111000;
            // JZ
            7'b1000_?11: Y <= 13'b0100_000_001000;
            7'b1000_?01: Y <= 13'b1000_000_001000;
            // JNZ
            7'b1001_?11: Y <= 13'b1000_000_001000;
            7'b1001_?01: Y <= 13'b0100_000_001000;
            // ADDI
            7'b1010_??1: Y <= 13'b0011_011_000010;
            // ADDM
            7'b1011_??1: Y <= 13'b1011_011_100000;
            // JMP
            7'b1100_??1: Y <= 13'b0100_000_001000;
            // OUT
            7'b1101_??1: Y <= 13'b0000_000_001001;
            // NANDI
            7'b1110_??1: Y <= 13'b0011_100_000010;
            // NANDM
            7'b1111_??1: Y <= 13'b1011_100_100000;
            default: Y <= 13'b1111111111111;
        endcase
//SE ASIGNA Y A LA SALIDA DEL DECODE
    assign controls = Y;
endmodule

//CODIGO FLIP FLOP D DE UN BIT
module FFP1(input wire clk, reset, enable, A, output reg Y);
 always @ (posedge clk or posedge reset) begin
    if (reset)
      Y <= 1'b0;
    else if(enable)
      Y <= A;
  end
endmodule

//CODIGO FLIP FLOP DE 4 BITS
module FFP4(input wire clk, reset, enable, input wire[3:0] A, output reg[3:0] Y);
 always @ (posedge clk or posedge reset) begin
    if (reset)
      Y <= 4'b0000;
    else if(enable)
      Y <= A;
  end
endmodule

//CODIGO DE FLAGS
module FLAGS(input clk, reset, enable, carry, zero, output wire c_flag, z_flag);
//2 FLIPFLOP DE 1 BIT PARA EL c_flag Y EL z_flag
  FFP1 U1(clk, reset, enable, zero, z_flag);
  FFP1 U2(clk, reset, enable, carry, c_flag);
endmodule

//CODIGO DE PHASE
module PHASE(input wire clk, reset, enable, output wire phase);
//SE USA UN FLIPFLOP NEGANDO LA ENTRADA
  FFP1 U1(clk, reset, enable, ~phase, phase);
endmodule

//CODIGO DE RAM
module RAM(input wire cs, we, input wire [11:0]address, inout[3:0] data);
//CODIGO PARA LEER Y ESCRIBIR RAM 
  reg[3:0]memoria[0:4095];
  reg[3:0]data_out;
  assign data = (cs && !we) ? data_out : 4'bz;

  always @ (address or cs or we) begin
    if (cs && !we) begin
      data_out = memoria[address];
    end
  end

  always @ (address or data or cs or we) begin
    if (cs && we) begin
      memoria[address] = data;
    end
  end
endmodule

//CODIGO DE uP
module uP(input wire clock, reset, input wire[3:0] pushbuttons, output wire phase, c_flag, z_flag, output wire[3:0] instr, oprnd, accu, data_bus, FF_out, output wire[7:0] program_byte, output wire[11:0] PC, address_RAM);
  wire Ze, C;
  wire[12:0] controls;
  wire[3:0] a;
  assign address_RAM = {oprnd, program_byte};
  PHASE PHASE1(clock, reset, 1'b1, phase);
  DECODE DECODE1({instr, c_flag, z_flag, phase}, controls);
  FETCH FETCH1(clock, reset, ~phase, program_byte, instr, oprnd);
  PC PC1(clock, reset, controls[12], controls[11], address_RAM, PC);
  BD BD1(controls[1], oprnd, data_bus);
  ROM ROM1(PC, program_byte);
  RAM RAM1(controls[5], controls[4], address_RAM, data_bus);
  FLAGS FLAGS1(clock, reset, controls[9], C, Ze, c_flag, z_flag);
  ALU ALU1(accu, data_bus, {controls[8],controls[7],controls[6]}, C, Ze, a);
  ACCU ACCU1(clock, reset, controls[10], a, accu);
  BD BD2(controls[3], a, data_bus);
  BD BD3(controls[2], pushbuttons, data_bus);
  FFP4 FFP44(clock, reset, controls[0], data_bus, FF_out);
endmodule

uP_tb.v
module testbench();

    reg clock, reset;
    reg [3:0] pushbuttons;
    wire phase, c_flag, z_flag;
    wire [3:0] instr, oprnd, accu, data_bus, FF_out;
    wire [7:0] program_byte;
    wire [11:0] PC, address_RAM;



    uP uPmodule(.clock(clock),
                .reset(reset),
                .pushbuttons(pushbuttons),
                .phase(phase),
                .c_flag(c_flag),
                .z_flag(z_flag),
                .instr(instr),
                .oprnd(oprnd),
                .accu(accu),
                .data_bus(data_bus),
                .FF_out(FF_out),
                .program_byte(program_byte),
                .PC(PC),
                .address_RAM(address_RAM));

    integer immediateDelay = 16;
    integer jumpDelay = 656;
    integer memoryDelay = 276;

    always
        #5 clock = ~clock;

    initial begin
      $display("uP");
      $display("clock  reset  pushbuttons | phase c_flag z_flag instr oprnd accu data_bus FF_out program_byte PC address_RAM");
      $display("-----------|---------");
      $monitor("%b %b %b | %b %b %b %b %b %b %b %b %b %b %b", clock, reset, pushbuttons, phase, c_flag, z_flag, instr, oprnd, accu, data_bus, FF_out, program_byte, PC, address_RAM);
          clock = 0; reset = 0; pushbuttons = 4'b0000;
      #5  reset = 1; pushbuttons = 4'b0001;
      #5  reset = 0; pushbuttons = 4'b0001;






    end

    initial
    #110 $finish;
    initial begin
      $dumpfile("uP_tb.vcd");
      $dumpvars(0, testbench);
    end
endmodule

uP_tb.vcd
$date
	Sun Nov 22 19:40:49 2020
$end
$version
	Icarus Verilog
$end
$timescale
	1ps
$end
$scope module testbench $end
$var wire 4 ! data_bus [3:0] $end
$var wire 1 " z_flag $end
$var wire 8 # program_byte [7:0] $end
$var wire 1 $ phase $end
$var wire 4 % oprnd [3:0] $end
$var wire 4 & instr [3:0] $end
$var wire 1 ' c_flag $end
$var wire 12 ( address_RAM [11:0] $end
$var wire 4 ) accu [3:0] $end
$var wire 12 * PC [11:0] $end
$var wire 4 + FF_out [3:0] $end
$var reg 1 , clock $end
$var reg 4 - pushbuttons [3:0] $end
$var reg 1 . reset $end
$var integer 32 / immediateDelay [31:0] $end
$var integer 32 0 jumpDelay [31:0] $end
$var integer 32 1 memoryDelay [31:0] $end
$scope module uPmodule $end
$var wire 1 , clock $end
$var wire 4 2 data_bus [3:0] $end
$var wire 4 3 pushbuttons [3:0] $end
$var wire 1 . reset $end
$var wire 1 " z_flag $end
$var wire 8 4 program_byte [7:0] $end
$var wire 1 $ phase $end
$var wire 4 5 oprnd [3:0] $end
$var wire 4 6 instr [3:0] $end
$var wire 13 7 controls [12:0] $end
$var wire 1 ' c_flag $end
$var wire 12 8 address_RAM [11:0] $end
$var wire 4 9 accu [3:0] $end
$var wire 4 : a [3:0] $end
$var wire 1 ; Ze $end
$var wire 12 < PC [11:0] $end
$var wire 4 = FF_out [3:0] $end
$var wire 1 > C $end
$scope module ACCU1 $end
$var wire 1 , clk $end
$var wire 1 ? enable $end
$var wire 1 . reset $end
$var wire 4 @ accu [3:0] $end
$var wire 4 A A [3:0] $end
$scope module F3 $end
$var wire 1 , clk $end
$var wire 1 ? enable $end
$var wire 1 . reset $end
$var wire 4 B A [3:0] $end
$var reg 4 C Y [3:0] $end
$upscope $end
$upscope $end
$scope module ALU1 $end
$var wire 4 D A [3:0] $end
$var wire 4 E B [3:0] $end
$var wire 3 F R [2:0] $end
$var wire 1 ; Ze $end
$var wire 4 G Y [3:0] $end
$var wire 1 > C $end
$var reg 5 H H [4:0] $end
$upscope $end
$scope module BD1 $end
$var wire 4 I data_bus [3:0] $end
$var wire 1 J enable $end
$var wire 4 K A [3:0] $end
$upscope $end
$scope module BD2 $end
$var wire 4 L A [3:0] $end
$var wire 4 M data_bus [3:0] $end
$var wire 1 N enable $end
$upscope $end
$scope module BD3 $end
$var wire 4 O A [3:0] $end
$var wire 4 P data_bus [3:0] $end
$var wire 1 Q enable $end
$upscope $end
$scope module DECODE1 $end
$var wire 7 R A [6:0] $end
$var wire 13 S controls [12:0] $end
$var reg 13 T Y [12:0] $end
$upscope $end
$scope module FETCH1 $end
$var wire 1 , clk $end
$var wire 1 U enable $end
$var wire 1 . reset $end
$var wire 4 V oprnd [3:0] $end
$var wire 4 W instr [3:0] $end
$var wire 8 X A [7:0] $end
$scope module F1 $end
$var wire 4 Y A [3:0] $end
$var wire 1 , clk $end
$var wire 1 U enable $end
$var wire 1 . reset $end
$var reg 4 Z Y [3:0] $end
$upscope $end
$scope module F2 $end
$var wire 4 [ A [3:0] $end
$var wire 1 , clk $end
$var wire 1 U enable $end
$var wire 1 . reset $end
$var reg 4 \ Y [3:0] $end
$upscope $end
$upscope $end
$scope module FFP44 $end
$var wire 4 ] A [3:0] $end
$var wire 1 , clk $end
$var wire 1 ^ enable $end
$var wire 1 . reset $end
$var reg 4 _ Y [3:0] $end
$upscope $end
$scope module FLAGS1 $end
$var wire 1 > carry $end
$var wire 1 , clk $end
$var wire 1 ` enable $end
$var wire 1 . reset $end
$var wire 1 ; zero $end
$var wire 1 " z_flag $end
$var wire 1 ' c_flag $end
$scope module U1 $end
$var wire 1 ; A $end
$var wire 1 , clk $end
$var wire 1 ` enable $end
$var wire 1 . reset $end
$var reg 1 " Y $end
$upscope $end
$scope module U2 $end
$var wire 1 > A $end
$var wire 1 , clk $end
$var wire 1 ` enable $end
$var wire 1 . reset $end
$var reg 1 ' Y $end
$upscope $end
$upscope $end
$scope module PC1 $end
$var wire 1 , clk $end
$var wire 1 a enable $end
$var wire 12 b load [11:0] $end
$var wire 1 c loadbit $end
$var wire 1 . reset $end
$var reg 12 d PC [11:0] $end
$upscope $end
$scope module PHASE1 $end
$var wire 1 , clk $end
$var wire 1 e enable $end
$var wire 1 . reset $end
$var wire 1 $ phase $end
$scope module U1 $end
$var wire 1 f A $end
$var wire 1 , clk $end
$var wire 1 e enable $end
$var wire 1 . reset $end
$var reg 1 $ Y $end
$upscope $end
$upscope $end
$scope module RAM1 $end
$var wire 12 g address [11:0] $end
$var wire 1 h cs $end
$var wire 4 i data [3:0] $end
$var wire 1 j we $end
$var reg 4 k data_out [3:0] $end
$upscope $end
$scope module ROM1 $end
$var wire 12 l A [11:0] $end
$var wire 8 m program_byte [7:0] $end
$upscope $end
$upscope $end
$upscope $end
$enddefinitions $end
#0
$dumpvars
bx m
bx l
bx k
xj
bx i
xh
bx g
xf
1e
bx d
xc
bx b
xa
x`
bx _
x^
bx ]
bx \
bx [
bx Z
bx Y
bx X
bx W
bx V
xU
bx T
bx S
bx R
xQ
bx P
b0 O
xN
bx M
bx L
bx K
xJ
bx I
bx H
bx G
bx F
bx E
bx D
bx C
bx B
bx A
bx @
x?
x>
bx =
bx <
x;
bx :
bx 9
bx 8
bx 7
bx 6
bx 5
bx 4
b0 3
bx 2
b100010100 1
b1010010000 0
b10000 /
0.
b0 -
0,
bx +
bx *
bx )
bx (
x'
bx &
bx %
x$
bx #
x"
bx !
$end
#5
b0 !
b0 2
b0 E
b0 I
b0 M
b0 P
b0 ]
b0 i
0^
0Q
1N
0?
b0 F
0`
0j
0h
0J
0c
1a
b1000000001000 7
b1000000001000 S
b1000000001000 T
1;
b0 :
b0 A
b0 B
b0 G
b0 L
0>
1f
1U
b110 [
b100 Y
b0 H
0$
b0 &
b0 6
b0 W
b0 Z
b0 %
b0 5
b0 K
b0 V
b0 \
b1000110 (
b1000110 8
b1000110 b
b1000110 g
b1000110 #
b1000110 4
b1000110 X
b1000110 m
b0 *
b0 <
b0 d
b0 l
0"
b0 R
0'
b0 )
b0 9
b0 @
b0 C
b0 D
b0 +
b0 =
b0 _
b1 -
b1 3
b1 O
1.
1,
#10
0.
0,
#15
0;
b110 :
b110 A
b110 B
b110 G
b110 L
b110 H
b110 !
b110 2
b110 E
b110 I
b110 M
b110 P
b110 ]
b110 i
0N
1?
b10 F
1`
1J
0a
b11010000010 7
b11010000010 S
b11010000010 T
b101 [
b101 Y
0f
0U
b1010101 #
b1010101 4
b1010101 X
b1010101 m
b1 *
b1 <
b1 d
b1 l
b11001010101 (
b11001010101 8
b11001010101 b
b11001010101 g
b110 %
b110 5
b110 K
b110 V
b110 \
b100 &
b100 6
b100 W
b100 Z
b100001 R
1$
1,
#20
0,
#25
b110 !
b110 2
b110 E
b110 I
b110 M
b110 P
b110 ]
b110 i
1N
0?
b0 F
0`
0J
1a
b1000000001000 7
b1000000001000 S
b1000000001000 T
1f
1U
b100000 R
0$
b110 )
b110 9
b110 @
b110 C
b110 D
1,
#30
0,
#35
b1 :
b1 A
b1 B
b1 G
b1 L
b1 H
b1 !
b1 2
b1 E
b1 I
b1 M
b1 P
b1 ]
b1 i
1Q
0N
1?
b10 F
1`
0a
b11010000100 7
b11010000100 S
b11010000100 T
b10 [
b1010 Y
0f
0U
b10100010 #
b10100010 4
b10100010 X
b10100010 m
b10 *
b10 <
b10 d
b10 l
b10110100010 (
b10110100010 8
b10110100010 b
b10110100010 g
b101 %
b101 5
b101 K
b101 V
b101 \
b101 &
b101 6
b101 W
b101 Z
b101001 R
1$
1,
#40
0,
#45
0Q
1N
0?
b0 F
0`
1a
b1000000001000 7
b1000000001000 S
b1000000001000 T
1f
1U
b101000 R
0$
b1 )
b1 9
b1 @
b1 C
b1 D
1,
#50
0,
#55
0;
b11 :
b11 A
b11 B
b11 G
b11 L
0>
b11 H
b10 !
b10 2
b10 E
b10 I
b10 M
b10 P
b10 ]
b10 i
0N
1?
b11 F
1`
1J
0a
b11011000010 7
b11011000010 S
b11011000010 T
b1 [
b0 Y
0f
0U
b1 #
b1 4
b1 X
b1 m
b11 *
b11 <
b11 d
b11 l
b1000000001 (
b1000000001 8
b1000000001 b
b1000000001 g
b10 %
b10 5
b10 K
b10 V
b10 \
b1010 &
b1010 6
b1010 W
b1010 Z
b1010001 R
1$
1,
#60
0,
#65
b11 !
b11 2
b11 E
b11 I
b11 M
b11 P
b11 ]
b11 i
1N
0?
b0 F
0`
0J
1a
b1000000001000 7
b1000000001000 S
b1000000001000 T
b11 :
b11 A
b11 B
b11 G
b11 L
1f
1U
b11 H
b1010000 R
0$
b11 )
b11 9
b11 @
b11 C
b11 D
1,
#70
0,
#75
b11 [
b1011 Y
0f
0U
b10110011 #
b10110011 4
b10110011 X
b10110011 m
b100 *
b100 <
b100 d
b100 l
b110110011 (
b110110011 8
b110110011 b
b110110011 g
b1 %
b1 5
b1 K
b1 V
b1 \
b0 &
b0 6
b0 W
b0 Z
b1 R
1$
1,
#80
0,
#85
1f
1U
b1 [
b0 Y
b0 R
0$
b100000001 (
b100000001 8
b100000001 b
b100000001 g
b1 #
b1 4
b1 X
b1 m
b101 *
b101 <
b101 d
b101 l
1,
#90
0,
#95
b1101 [
b1100 Y
0f
0U
b111001101 (
b111001101 8
b111001101 b
b111001101 g
b11001101 #
b11001101 4
b11001101 X
b11001101 m
b110 *
b110 <
b110 d
b110 l
b1 R
1$
1,
#100
0,
#105
1f
1U
b1 [
b0 Y
b0 R
0$
b100000001 (
b100000001 8
b100000001 b
b100000001 g
b1 #
b1 4
b1 X
b1 m
b111 *
b111 <
b111 d
b111 l
1,
